[
    {
        "bossName": "Ragnaros",
        "expansion": "classic",
        "itemId": 17182,
        "itemName": "Sulfuras, Hand of Ragnaros",
        "slot": "Two-Hand",
        "quality": "Legendary",
        "itemLevel": 80,
        "dropRate": 0.0400,
        "classRestrictions": null,
        "iconUrl": "https://wow.zamimg.com/images/wow/icons/large/inv_hammer_unique_sulfuras.jpg"
    },
    {
        "bossName": "Ragnaros",
        "expansion": "classic",
        "itemId": 17063,
        "itemName": "Band of Accuria",
        "slot": "Finger",
        "quality": "Epic",
        "itemLevel": 78,
        "dropRate": 0.1200,
        "classRestrictions": null,
        "iconUrl": "https://wow.zamimg.com/images/wow/icons/large/inv_jewelry_ring_23.jpg"
    },
    {
        "bossName": "Ragnaros",
        "expansion": "classic",
        "itemId": 17076,
        "itemName": "Bonereaver's Edge",
        "slot": "Two-Hand",
        "quality": "Epic",
        "itemLevel": 77,
        "dropRate": 0.0700,
        "classRestrictions": [
            "Warrior",
            "Paladin"
        ],
        "iconUrl": "https://wow.zamimg.com/images/wow/icons/large/inv_sword_31.jpg"
    },
    {
        "bossName": "Ragnaros",
        "expansion": "classic",
        "itemId": 17082,
        "itemName": "Shard of the Flame",
        "slot": "Trinket",
        "quality": "Epic",
        "itemLevel": 74,
        "dropRate": 0.1000,
        "classRestrictions": null,
        "iconUrl": "https://wow.zamimg.com/images/wow/icons/large/inv_trinket_naxxramas06.jpg"
    },
    {
        "bossName": "Lucifron",
        "expansion": "classic",
        "itemId": 16806,
        "itemName": "Felheart Belt",
        "slot": "Waist",
        "quality": "Epic",
        "itemLevel": 66,
        "dropRate": 0.1500,
        "classRestrictions": [
            "Warlock"
        ],
        "iconUrl": "https://wow.zamimg.com/images/wow/icons/large/inv_belt_13.jpg"
    },
    {
        "bossName": "Garr",
        "expansion": "classic",
        "itemId": 18564,
        "itemName": "Bindings of the Windseeker",
        "slot": "Quest",
        "quality": "Legendary",
        "itemLevel": 75,
        "dropRate": 0.0300,
        "classRestrictions": null,
        "iconUrl": "https://wow.zamimg.com/images/wow/icons/large/inv_misc_stonetablet_11.jpg"
    },
    {
        "bossName": "Baron Geddon",
        "expansion": "classic",
        "itemId": 18563,
        "itemName": "Bindings of the Windseeker",
        "slot": "Quest",
        "quality": "Legendary",
        "itemLevel": 75,
        "dropRate": 0.0300,
        "classRestrictions": null,
        "iconUrl": "https://wow.zamimg.com/images/wow/icons/large/inv_misc_stonetablet_11.jpg"
    },
    {
        "bossName": "Golemagg the Incinerator",
        "expansion": "classic",
        "itemId": 17103,
        "itemName": "Azuresong Mageblade",
        "slot": "One-Hand",
        "quality": "Epic",
        "itemLevel": 71,
        "dropRate": 0.1000,
        "classRestrictions": [
            "Mage",
            "Warlock",
            "Paladin"
        ],
        "iconUrl": "https://wow.zamimg.com/images/wow/icons/large/inv_sword_26.jpg"
    },
    {
        "bossName": "Nefarian",
        "expansion": "classic",
        "itemId": 19375,
        "itemName": "Mish'undare, Circlet of the Mind Flayer",
        "slot": "Head",
        "quality": "Epic",
        "itemLevel": 83,
        "dropRate": 0.1000,
        "classRestrictions": null,
        "iconUrl": "https://wow.zamimg.com/images/wow/icons/large/inv_helmet_19.jpg"
    },
    {
        "bossName": "Nefarian",
        "expansion": "classic",
        "itemId": 19377,
        "itemName": "Prestor's Talisman of Connivery",
        "slot": "Neck",
        "quality": "Epic",
        "itemLevel": 83,
        "dropRate": 0.0800,
        "classRestrictions": null,
        "iconUrl": "https://wow.zamimg.com/images/wow/icons/large/inv_jewelry_necklace_15.jpg"
    },
    {
        "bossName": "Chromaggus",
        "expansion": "classic",
        "itemId": 19389,
        "itemName": "Taut Dragonhide Shoulderpads",
        "slot": "Shoulder",
        "quality": "Epic",
        "itemLevel": 77,
        "dropRate": 0.0700,
        "classRestrictions": [
            "Druid",
            "Rogue"
        ],
        "iconUrl": "https://wow.zamimg.com/images/wow/icons/large/inv_shoulder_08.jpg"
    },
    {
        "bossName": "Onyxia",
        "expansion": "classic",
        "itemId": 18422,
        "itemName": "Head of Onyxia",
        "slot": "Quest",
        "quality": "Epic",
        "itemLevel": 60,
        "dropRate": 1.0000,
        "classRestrictions": null,
        "iconUrl": "https://wow.zamimg.com/images/wow/icons/large/inv_misc_head_dragon_01.jpg"
    },
    {
        "bossName": "Onyxia",
        "expansion": "classic",
        "itemId": 17068,
        "itemName": "Deathbringer",
        "slot": "One-Hand",
        "quality": "Epic",
        "itemLevel": 75,
        "dropRate": 0.0800,
        "classRestrictions": null,
        "iconUrl": "https://wow.zamimg.com/images/wow/icons/large/inv_axe_06.jpg"
    },
    {
        "bossName": "C'Thun",
        "expansion": "classic",
        "itemId": 21221,
        "itemName": "Eye of C'Thun",
        "slot": "Quest",
        "quality": "Epic",
        "itemLevel": 60,
        "dropRate": 1.0000,
        "classRestrictions": null,
        "iconUrl": "https://wow.zamimg.com/images/wow/icons/large/inv_misc_eye_01.jpg"
    },
    {
        "bossName": "C'Thun",
        "expansion": "classic",
        "itemId": 21126,
        "itemName": "Death's Sting",
        "slot": "One-Hand",
        "quality": "Epic",
        "itemLevel": 84,
        "dropRate": 0.0700,
        "classRestrictions": [
            "Rogue",
            "Warrior"
        ],
        "iconUrl": "https://wow.zamimg.com/images/wow/icons/large/inv_weapon_shortblade_07.jpg"
    },
    {
        "bossName": "Kel'Thuzad",
        "expansion": "classic",
        "itemId": 23054,
        "itemName": "Gressil, Dawn of Ruin",
        "slot": "One-Hand",
        "quality": "Epic",
        "itemLevel": 89,
        "dropRate": 0.0500,
        "classRestrictions": [
            "Warrior",
            "Rogue"
        ],
        "iconUrl": "https://wow.zamimg.com/images/wow/icons/large/inv_sword_40.jpg"
    },
    {
        "bossName": "Kel'Thuzad",
        "expansion": "classic",
        "itemId": 23577,
        "itemName": "The Hungering Cold",
        "slot": "One-Hand",
        "quality": "Epic",
        "itemLevel": 89,
        "dropRate": 0.0500,
        "classRestrictions": null,
        "iconUrl": "https://wow.zamimg.com/images/wow/icons/large/inv_sword_56.jpg"
    },
    {
        "bossName": "Sapphiron",
        "expansion": "classic",
        "itemId": 23050,
        "itemName": "Cloak of the Necropolis",
        "slot": "Back",
        "quality": "Epic",
        "itemLevel": 90,
        "dropRate": 0.0800,
        "classRestrictions": null,
        "iconUrl": "https://wow.zamimg.com/images/wow/icons/large/inv_misc_cape_18.jpg"
    },
    {
        "bossName": "Edwin VanCleef",
        "expansion": "classic",
        "itemId": 5191,
        "itemName": "Cruel Barb",
        "slot": "One-Hand",
        "quality": "Rare",
        "itemLevel": 24,
        "dropRate": 0.2000,
        "classRestrictions": null,
        "iconUrl": "https://wow.zamimg.com/images/wow/icons/large/inv_sword_27.jpg"
    },
    {
        "bossName": "Interrogator Vishas",
        "expansion": "classic",
        "itemId": 7682,
        "itemName": "Torturing Poker",
        "slot": "One-Hand",
        "quality": "Rare",
        "itemLevel": 34,
        "dropRate": 0.3000,
        "classRestrictions": null,
        "iconUrl": "https://wow.zamimg.com/images/wow/icons/large/inv_weapon_shortblade_03.jpg"
    },
    {
        "bossName": "Interrogator Vishas",
        "expansion": "classic",
        "itemId": 7683,
        "itemName": "Bloody Brass Knuckles",
        "slot": "Hands",
        "quality": "Uncommon",
        "itemLevel": 34,
        "dropRate": 0.3500,
        "classRestrictions": null,
        "iconUrl": "https://wow.zamimg.com/images/wow/icons/large/inv_gauntlets_04.jpg"
    },
    {
        "bossName": "Bloodmage Thalnos",
        "expansion": "classic",
        "itemId": 7685,
        "itemName": "Orb of the Forgotten Seer",
        "slot": "Off Hand",
        "quality": "Rare",
        "itemLevel": 38,
        "dropRate": 0.3000,
        "classRestrictions": null,
        "iconUrl": "https://wow.zamimg.com/images/wow/icons/large/inv_misc_orb_03.jpg"
    },
    {
        "bossName": "Bloodmage Thalnos",
        "expansion": "classic",
        "itemId": 7684,
        "itemName": "Bloodmage Mantle",
        "slot": "Shoulder",
        "quality": "Uncommon",
        "itemLevel": 35,
        "dropRate": 0.3500,
        "classRestrictions": null,
        "iconUrl": "https://wow.zamimg.com/images/wow/icons/large/inv_shoulder_02.jpg"
    },
    {
        "bossName": "Houndmaster Loksey",
        "expansion": "classic",
        "itemId": 7710,
        "itemName": "Loksey's Training Stick",
        "slot": "Two-Hand",
        "quality": "Rare",
        "itemLevel": 36,
        "dropRate": 0.3000,
        "classRestrictions": null,
        "iconUrl": "https://wow.zamimg.com/images/wow/icons/large/inv_staff_08.jpg"
    },
    {
        "bossName": "Houndmaster Loksey",
        "expansion": "classic",
        "itemId": 7756,
        "itemName": "Dog Training Gloves",
        "slot": "Hands",
        "quality": "Rare",
        "itemLevel": 34,
        "dropRate": 0.3500,
        "classRestrictions": null,
        "iconUrl": "https://wow.zamimg.com/images/wow/icons/large/inv_gauntlets_11.jpg"
    },
    {
        "bossName": "Arcanist Doan",
        "expansion": "classic",
        "itemId": 7714,
        "itemName": "Hypnotic Blade",
        "slot": "Main Hand",
        "quality": "Rare",
        "itemLevel": 39,
        "dropRate": 0.2500,
        "classRestrictions": null,
        "iconUrl": "https://wow.zamimg.com/images/wow/icons/large/inv_weapon_shortblade_05.jpg"
    },
    {
        "bossName": "Arcanist Doan",
        "expansion": "classic",
        "itemId": 7713,
        "itemName": "Illusionary Rod",
        "slot": "Two-Hand",
        "quality": "Rare",
        "itemLevel": 39,
        "dropRate": 0.2500,
        "classRestrictions": null,
        "iconUrl": "https://wow.zamimg.com/images/wow/icons/large/inv_staff_01.jpg"
    },
    {
        "bossName": "Arcanist Doan",
        "expansion": "classic",
        "itemId": 7712,
        "itemName": "Mantle of Doan",
        "slot": "Shoulder",
        "quality": "Uncommon",
        "itemLevel": 38,
        "dropRate": 0.3000,
        "classRestrictions": null,
        "iconUrl": "https://wow.zamimg.com/images/wow/icons/large/inv_shoulder_02.jpg"
    },
    {
        "bossName": "Arcanist Doan",
        "expansion": "classic",
        "itemId": 7711,
        "itemName": "Robe of Doan",
        "slot": "Chest",
        "quality": "Uncommon",
        "itemLevel": 38,
        "dropRate": 0.3000,
        "classRestrictions": null,
        "iconUrl": "https://wow.zamimg.com/images/wow/icons/large/inv_chest_cloth_04.jpg"
    },
    {
        "bossName": "Herod",
        "expansion": "classic",
        "itemId": 7717,
        "itemName": "Ravager",
        "slot": "Two-Hand",
        "quality": "Rare",
        "itemLevel": 42,
        "dropRate": 0.1200,
        "classRestrictions": null,
        "iconUrl": "https://wow.zamimg.com/images/wow/icons/large/inv_weapon_halberd_05.jpg"
    },
    {
        "bossName": "Herod",
        "expansion": "classic",
        "itemId": 7718,
        "itemName": "Herod's Shoulder",
        "slot": "Shoulder",
        "quality": "Rare",
        "itemLevel": 42,
        "dropRate": 0.2500,
        "classRestrictions": null,
        "iconUrl": "https://wow.zamimg.com/images/wow/icons/large/inv_shoulder_01.jpg"
    },
    {
        "bossName": "Herod",
        "expansion": "classic",
        "itemId": 7719,
        "itemName": "Raging Berserker's Helm",
        "slot": "Head",
        "quality": "Rare",
        "itemLevel": 42,
        "dropRate": 0.2500,
        "classRestrictions": null,
        "iconUrl": "https://wow.zamimg.com/images/wow/icons/large/inv_helmet_09.jpg"
    },
    {
        "bossName": "Herod",
        "expansion": "classic",
        "itemId": 10330,
        "itemName": "Scarlet Leggings",
        "slot": "Legs",
        "quality": "Rare",
        "itemLevel": 43,
        "dropRate": 0.2000,
        "classRestrictions": null,
        "iconUrl": "https://wow.zamimg.com/images/wow/icons/large/inv_pants_04.jpg"
    },
    {
        "bossName": "Scarlet Commander Mograine",
        "expansion": "classic",
        "itemId": 7726,
        "itemName": "Aegis of the Scarlet Commander",
        "slot": "Off Hand",
        "quality": "Rare",
        "itemLevel": 44,
        "dropRate": 0.2000,
        "classRestrictions": null,
        "iconUrl": "https://wow.zamimg.com/images/wow/icons/large/inv_shield_04.jpg"
    },
    {
        "bossName": "Scarlet Commander Mograine",
        "expansion": "classic",
        "itemId": 7723,
        "itemName": "Mograine's Might",
        "slot": "Two-Hand",
        "quality": "Rare",
        "itemLevel": 44,
        "dropRate": 0.2000,
        "classRestrictions": null,
        "iconUrl": "https://wow.zamimg.com/images/wow/icons/large/inv_mace_10.jpg"
    },
    {
        "bossName": "Scarlet Commander Mograine",
        "expansion": "classic",
        "itemId": 7724,
        "itemName": "Gauntlets of Divinity",
        "slot": "Hands",
        "quality": "Rare",
        "itemLevel": 44,
        "dropRate": 0.2000,
        "classRestrictions": null,
        "iconUrl": "https://wow.zamimg.com/images/wow/icons/large/inv_gauntlets_29.jpg"
    },
    {
        "bossName": "High Inquisitor Whitemane",
        "expansion": "classic",
        "itemId": 7720,
        "itemName": "Whitemane's Chapeau",
        "slot": "Head",
        "quality": "Rare",
        "itemLevel": 44,
        "dropRate": 0.2000,
        "classRestrictions": null,
        "iconUrl": "https://wow.zamimg.com/images/wow/icons/large/inv_helmet_38.jpg"
    },
    {
        "bossName": "High Inquisitor Whitemane",
        "expansion": "classic",
        "itemId": 7721,
        "itemName": "Hand of Righteousness",
        "slot": "Two-Hand",
        "quality": "Rare",
        "itemLevel": 44,
        "dropRate": 0.2000,
        "classRestrictions": null,
        "iconUrl": "https://wow.zamimg.com/images/wow/icons/large/inv_mace_02.jpg"
    },
    {
        "bossName": "High Inquisitor Whitemane",
        "expansion": "classic",
        "itemId": 7722,
        "itemName": "Triune Amulet",
        "slot": "Neck",
        "quality": "Rare",
        "itemLevel": 44,
        "dropRate": 0.2000,
        "classRestrictions": null,
        "iconUrl": "https://wow.zamimg.com/images/wow/icons/large/inv_jewelry_amulet_01.jpg"
    },
    {
        "bossName": "The Curator",
        "expansion": "tbc",
        "itemId": 28633,
        "itemName": "Staff of Infinite Mysteries",
        "slot": "Two-Hand",
        "quality": "Epic",
        "itemLevel": 115,
        "dropRate": 0.1000,
        "classRestrictions": null,
        "iconUrl": "https://wow.zamimg.com/images/wow/icons/large/inv_staff_29.jpg"
    },
    {
        "bossName": "Prince Malchezaar",
        "expansion": "tbc",
        "itemId": 28611,
        "itemName": "Dragonheart Flameshield",
        "slot": "Off Hand",
        "quality": "Epic",
        "itemLevel": 115,
        "dropRate": 0.1200,
        "classRestrictions": null,
        "iconUrl": "https://wow.zamimg.com/images/wow/icons/large/inv_shield_30.jpg"
    },
    {
        "bossName": "Attumen the Huntsman",
        "expansion": "tbc",
        "itemId": 28477,
        "itemName": "Harbinger Bands",
        "slot": "Wrist",
        "quality": "Epic",
        "itemLevel": 115,
        "dropRate": 0.1500,
        "classRestrictions": null,
        "iconUrl": "https://wow.zamimg.com/images/wow/icons/large/inv_bracer_02.jpg"
    },
    {
        "bossName": "Attumen the Huntsman",
        "expansion": "tbc",
        "itemId": 30480,
        "itemName": "Fiery Warhorse's Reins",
        "slot": "Mount",
        "quality": "Epic",
        "itemLevel": 1,
        "dropRate": 0.0100,
        "classRestrictions": null,
        "iconUrl": "https://wow.zamimg.com/images/wow/icons/large/ability_mount_dreadsteed.jpg"
    },
    {
        "bossName": "The Curator",
        "expansion": "tbc",
        "itemId": 28649,
        "itemName": "Garona's Signet Ring",
        "slot": "Finger",
        "quality": "Epic",
        "itemLevel": 115,
        "dropRate": 0.1000,
        "classRestrictions": null,
        "iconUrl": "https://wow.zamimg.com/images/wow/icons/large/inv_jewelry_ring_57.jpg"
    },
    {
        "bossName": "Lady Vashj",
        "expansion": "tbc",
        "itemId": 30021,
        "itemName": "Fang of Vashj",
        "slot": "One-Hand",
        "quality": "Epic",
        "itemLevel": 141,
        "dropRate": 0.0800,
        "classRestrictions": null,
        "iconUrl": "https://wow.zamimg.com/images/wow/icons/large/inv_weapon_shortblade_47.jpg"
    },
    {
        "bossName": "Kael'thas Sunstrider",
        "expansion": "tbc",
        "itemId": 30311,
        "itemName": "Warp Slicer",
        "slot": "One-Hand",
        "quality": "Legendary",
        "itemLevel": 175,
        "dropRate": 0.1000,
        "classRestrictions": null,
        "iconUrl": "https://wow.zamimg.com/images/wow/icons/large/inv_sword_75.jpg"
    },
    {
        "bossName": "Kael'thas Sunstrider",
        "expansion": "tbc",
        "itemId": 32458,
        "itemName": "Ashes of Al'ar",
        "slot": "Mount",
        "quality": "Legendary",
        "itemLevel": 70,
        "dropRate": 0.0200,
        "classRestrictions": null,
        "iconUrl": "https://wow.zamimg.com/images/wow/icons/large/inv_misc_summerfest_brazierorange.jpg"
    },
    {
        "bossName": "Illidan Stormrage",
        "expansion": "tbc",
        "itemId": 32837,
        "itemName": "Warglaive of Azzinoth",
        "slot": "Main Hand",
        "quality": "Legendary",
        "itemLevel": 156,
        "dropRate": 0.0500,
        "classRestrictions": [
            "Warrior",
            "Rogue"
        ],
        "iconUrl": "https://wow.zamimg.com/images/wow/icons/large/inv_weapon_glave_01.jpg"
    },
    {
        "bossName": "Illidan Stormrage",
        "expansion": "tbc",
        "itemId": 32838,
        "itemName": "Warglaive of Azzinoth",
        "slot": "Off Hand",
        "quality": "Legendary",
        "itemLevel": 156,
        "dropRate": 0.0500,
        "classRestrictions": [
            "Warrior",
            "Rogue"
        ],
        "iconUrl": "https://wow.zamimg.com/images/wow/icons/large/inv_weapon_glave_01.jpg"
    },
    {
        "bossName": "Kil'jaeden",
        "expansion": "tbc",
        "itemId": 34334,
        "itemName": "Thori'dal, the Stars' Fury",
        "slot": "Ranged",
        "quality": "Legendary",
        "itemLevel": 164,
        "dropRate": 0.0300,
        "classRestrictions": [
            "Hunter",
            "Rogue",
            "Warrior"
        ],
        "iconUrl": "https://wow.zamimg.com/images/wow/icons/large/inv_weapon_bow_39.jpg"
    },
    {
        "bossName": "Yogg-Saron",
        "expansion": "wotlk",
        "itemId": 46017,
        "itemName": "Val'anyr, Hammer of Ancient Kings",
        "slot": "Main Hand",
        "quality": "Legendary",
        "itemLevel": 245,
        "dropRate": 0.0100,
        "classRestrictions": [
            "Paladin",
            "Priest",
            "Druid",
            "Shaman"
        ],
        "iconUrl": "https://wow.zamimg.com/images/wow/icons/large/inv_mace_99.jpg"
    },
    {
        "bossName": "Yogg-Saron",
        "expansion": "wotlk",
        "itemId": 45529,
        "itemName": "Ironmender",
        "slot": "Wrist",
        "quality": "Epic",
        "itemLevel": 232,
        "dropRate": 0.1000,
        "classRestrictions": null,
        "iconUrl": "https://wow.zamimg.com/images/wow/icons/large/inv_bracer_28.jpg"
    },
    {
        "bossName": "Algalon the Observer",
        "expansion": "wotlk",
        "itemId": 45609,
        "itemName": "Comet's Trail",
        "slot": "Trinket",
        "quality": "Epic",
        "itemLevel": 239,
        "dropRate": 0.1500,
        "classRestrictions": null,
        "iconUrl": "https://wow.zamimg.com/images/wow/icons/large/spell_arcane_starfire.jpg"
    },
    {
        "bossName": "Mimiron",
        "expansion": "wotlk",
        "itemId": 45489,
        "itemName": "Pandora's Plea",
        "slot": "Trinket",
        "quality": "Epic",
        "itemLevel": 232,
        "dropRate": 0.1000,
        "classRestrictions": null,
        "iconUrl": "https://wow.zamimg.com/images/wow/icons/large/inv_misc_enggizmos_16.jpg"
    },
    {
        "bossName": "Hodir",
        "expansion": "wotlk",
        "itemId": 45461,
        "itemName": "Drape of Icy Intent",
        "slot": "Back",
        "quality": "Epic",
        "itemLevel": 232,
        "dropRate": 0.1000,
        "classRestrictions": null,
        "iconUrl": "https://wow.zamimg.com/images/wow/icons/large/inv_misc_cape_19.jpg"
    },
    {
        "bossName": "The Lich King",
        "expansion": "wotlk",
        "itemId": 50818,
        "itemName": "Invincible's Reins",
        "slot": "Mount",
        "quality": "Epic",
        "itemLevel": 80,
        "dropRate": 0.0100,
        "classRestrictions": null,
        "iconUrl": "https://wow.zamimg.com/images/wow/icons/large/ability_mount_yourockziliak.jpg"
    },
    {
        "bossName": "The Lich King",
        "expansion": "wotlk",
        "itemId": 50070,
        "itemName": "Glorenzelg, High-Blade of the Silver Hand",
        "slot": "Two-Hand",
        "quality": "Epic",
        "itemLevel": 277,
        "dropRate": 0.0800,
        "classRestrictions": [
            "Warrior",
            "Paladin",
            "Death Knight"
        ],
        "iconUrl": "https://wow.zamimg.com/images/wow/icons/large/inv_sword_141.jpg"
    },
    {
        "bossName": "The Lich King",
        "expansion": "wotlk",
        "itemId": 50012,
        "itemName": "Havoc's Call, Blade of Lordaeron Kings",
        "slot": "One-Hand",
        "quality": "Epic",
        "itemLevel": 277,
        "dropRate": 0.0800,
        "classRestrictions": null,
        "iconUrl": "https://wow.zamimg.com/images/wow/icons/large/inv_sword_132.jpg"
    },
    {
        "bossName": "Professor Putricide",
        "expansion": "wotlk",
        "itemId": 50231,
        "itemName": "Astrylian's Sutured Cinch",
        "slot": "Waist",
        "quality": "Epic",
        "itemLevel": 264,
        "dropRate": 0.1000,
        "classRestrictions": null,
        "iconUrl": "https://wow.zamimg.com/images/wow/icons/large/inv_belt_49c.jpg"
    },
    {
        "bossName": "Sindragosa",
        "expansion": "wotlk",
        "itemId": 50424,
        "itemName": "Memory of Malygos",
        "slot": "Trinket",
        "quality": "Epic",
        "itemLevel": 264,
        "dropRate": 0.0800,
        "classRestrictions": null,
        "iconUrl": "https://wow.zamimg.com/images/wow/icons/large/inv_misc_gem_pearl_12.jpg"
    },
    {
        "bossName": "Ragnaros",
        "expansion": "cata",
        "itemId": 69897,
        "itemName": "Sulfuras, the Extinguished Hand",
        "slot": "Two-Hand",
        "quality": "Legendary",
        "itemLevel": 391,
        "dropRate": 0.0100,
        "classRestrictions": null,
        "iconUrl": "https://wow.zamimg.com/images/wow/icons/large/inv_hammer_unique_sulfuras.jpg"
    },
    {
        "bossName": "Ragnaros",
        "expansion": "cata",
        "itemId": 71355,
        "itemName": "Majordomo's Chain of Office",
        "slot": "Neck",
        "quality": "Epic",
        "itemLevel": 384,
        "dropRate": 0.1000,
        "classRestrictions": null,
        "iconUrl": "https://wow.zamimg.com/images/wow/icons/large/inv_jewelry_necklace_43.jpg"
    },
    {
        "bossName": "Majordomo Staghelm",
        "expansion": "cata",
        "itemId": 71343,
        "itemName": "Fandral's Flamescythe",
        "slot": "Two-Hand",
        "quality": "Epic",
        "itemLevel": 378,
        "dropRate": 0.0800,
        "classRestrictions": [
            "Druid"
        ],
        "iconUrl": "https://wow.zamimg.com/images/wow/icons/large/inv_staff_99.jpg"
    },
    {
        "bossName": "Beth'tilac",
        "expansion": "cata",
        "itemId": 71039,
        "itemName": "Funeral Pyre",
        "slot": "Main Hand",
        "quality": "Epic",
        "itemLevel": 378,
        "dropRate": 0.1000,
        "classRestrictions": null,
        "iconUrl": "https://wow.zamimg.com/images/wow/icons/large/inv_sword_135.jpg"
    },
    {
        "bossName": "Alysrazor",
        "expansion": "cata",
        "itemId": 71079,
        "itemName": "Alysrazor's Band",
        "slot": "Finger",
        "quality": "Epic",
        "itemLevel": 378,
        "dropRate": 0.1200,
        "classRestrictions": null,
        "iconUrl": "https://wow.zamimg.com/images/wow/icons/large/inv_jewelry_ring_67.jpg"
    },
    {
        "bossName": "Madness of Deathwing",
        "expansion": "cata",
        "itemId": 77949,
        "itemName": "Gurthalak, Voice of the Deeps",
        "slot": "Two-Hand",
        "quality": "Epic",
        "itemLevel": 397,
        "dropRate": 0.0800,
        "classRestrictions": [
            "Warrior",
            "Paladin",
            "Death Knight"
        ],
        "iconUrl": "https://wow.zamimg.com/images/wow/icons/large/inv_sword_2h_deathwingraid_d_01.jpg"
    },
    {
        "bossName": "Madness of Deathwing",
        "expansion": "cata",
        "itemId": 77947,
        "itemName": "No'Kaled, the Elements of Death",
        "slot": "One-Hand",
        "quality": "Epic",
        "itemLevel": 397,
        "dropRate": 0.0800,
        "classRestrictions": null,
        "iconUrl": "https://wow.zamimg.com/images/wow/icons/large/inv_sword_1h_deathwingraid_d_01.jpg"
    },
    {
        "bossName": "Spine of Deathwing",
        "expansion": "cata",
        "itemId": 78357,
        "itemName": "Backbreaker Spaulders",
        "slot": "Shoulder",
        "quality": "Epic",
        "itemLevel": 397,
        "dropRate": 0.1000,
        "classRestrictions": null,
        "iconUrl": "https://wow.zamimg.com/images/wow/icons/large/inv_shoulder_plate_deathwingraid_d_01.jpg"
    },
    {
        "bossName": "Nefarian",
        "expansion": "cata",
        "itemId": 65003,
        "itemName": "Prestor's Talisman of Machination",
        "slot": "Neck",
        "quality": "Epic",
        "itemLevel": 359,
        "dropRate": 0.1000,
        "classRestrictions": null,
        "iconUrl": "https://wow.zamimg.com/images/wow/icons/large/inv_jewelry_necklace_30.jpg"
    },
    {
        "bossName": "Magmaw",
        "expansion": "cata",
        "itemId": 65022,
        "itemName": "Incineratus",
        "slot": "Main Hand",
        "quality": "Epic",
        "itemLevel": 359,
        "dropRate": 0.1200,
        "classRestrictions": null,
        "iconUrl": "https://wow.zamimg.com/images/wow/icons/large/inv_sword_110.jpg"
    },
    {
        "bossName": "Aku'mai (SoD)",
        "expansion": "sod",
        "itemId": 211505,
        "itemName": "Blackfathom Ritual Dagger",
        "slot": "Main Hand",
        "quality": "Rare",
        "itemLevel": 26,
        "dropRate": 0.1500,
        "classRestrictions": null,
        "iconUrl": null
    },
    {
        "bossName": "Aku'mai (SoD)",
        "expansion": "sod",
        "itemId": 211507,
        "itemName": "Twilight Sage's Walking Stick",
        "slot": "Two-Hand",
        "quality": "Rare",
        "itemLevel": 26,
        "dropRate": 0.1500,
        "classRestrictions": null,
        "iconUrl": null
    },
    {
        "bossName": "Twilight Lord Kelris (SoD)",
        "expansion": "sod",
        "itemId": 211508,
        "itemName": "Kelris's Scepter",
        "slot": "Main Hand",
        "quality": "Rare",
        "itemLevel": 25,
        "dropRate": 0.1500,
        "classRestrictions": null,
        "iconUrl": null
    },
    {
        "bossName": "Mekgineer Thermaplugg (SoD)",
        "expansion": "sod",
        "itemId": 213320,
        "itemName": "Thermaplugg's Rocket Launcher",
        "slot": "Ranged",
        "quality": "Rare",
        "itemLevel": 40,
        "dropRate": 0.1200,
        "classRestrictions": [
            "Warrior",
            "Hunter",
            "Rogue"
        ],
        "iconUrl": null
    },
    {
        "bossName": "Shade of Eranikus (SoD)",
        "expansion": "sod",
        "itemId": 220608,
        "itemName": "Eranikus's Scale",
        "slot": "Shield",
        "quality": "Epic",
        "itemLevel": 50,
        "dropRate": 0.1000,
        "classRestrictions": [
            "Warrior",
            "Paladin",
            "Shaman"
        ],
        "iconUrl": null
    }
]
